regfusion/__init__.py
regfusion/cli.py
regfusion/main.py
regfusion/mappings/lh.avgMapping_allSub_RF_ANTs_Colin27_orig_to_fsaverage.txt
regfusion/mappings/lh.avgMapping_allSub_RF_ANTs_MNI152_orig_to_fsaverage.txt
regfusion/mappings/lh.avgMapping_allSub_RF_M3Z_Colin27_norm_to_fsaverage.txt
regfusion/mappings/lh.avgMapping_allSub_RF_M3Z_MNI152_norm_to_fsaverage.txt
regfusion/mappings/rh.avgMapping_allSub_RF_ANTs_Colin27_orig_to_fsaverage.txt
regfusion/mappings/rh.avgMapping_allSub_RF_ANTs_MNI152_orig_to_fsaverage.txt
regfusion/mappings/rh.avgMapping_allSub_RF_M3Z_Colin27_norm_to_fsaverage.txt
regfusion/mappings/rh.avgMapping_allSub_RF_M3Z_MNI152_norm_to_fsaverage.txt
regfusion-0.1.0.dist-info/LICENSE
regfusion-0.1.0.dist-info/METADATA
regfusion-0.1.0.dist-info/WHEEL
regfusion-0.1.0.dist-info/entry_points.txt
regfusion-0.1.0.dist-info/top_level.txt
regfusion-0.1.0.dist-info/RECORD
