Metadata-Version: 2.1
Name: regfusion
Version: 0.1.0
Summary: Python implementation of registration fustion methods
Home-page: https://github.com/danjgale/reg-fusion
Maintainer: Dan Gale
Maintainer-email: d.gale@queensu.ca
License: MIT
Platform: UNKNOWN
Classifier: Programming Language :: Python :: 3
Classifier: Operating System :: OS Independent
Classifier: Intended Audience :: Science/Research
Classifier: Intended Audience :: Developers
Classifier: Topic :: Scientific/Engineering
Requires-Dist: numpy (>=1.11)
Requires-Dist: scipy (>=0.19)
Requires-Dist: nibabel (>=3.0.0)
Requires-Dist: nilearn (>=0.6.2)
